Metadata-Version: 1.0
Name: page-query
Version: 0.1.5
Summary: collect, index and query pages from everywhere
Home-page: UNKNOWN
Author: amazinglzy
Author-email: forlearn_lzy@163.com
License: UNKNOWN
Platform: UNKNOWN
